bitcoinalert.py
bitcoinAlertWithTelegram-1.0.0.dist-info/LICENSE.txt
bitcoinAlertWithTelegram-1.0.0.dist-info/METADATA
bitcoinAlertWithTelegram-1.0.0.dist-info/WHEEL
bitcoinAlertWithTelegram-1.0.0.dist-info/top_level.txt
bitcoinAlertWithTelegram-1.0.0.dist-info/RECORD
