Metadata-Version: 2.1
Name: bitcoinAlertWithTelegram
Version: 1.0.0
Summary: A package that allows to sent bitcoin alerts throgh IFTTT
Home-page: UNKNOWN
Author: Praveen
Author-email: praveenacchusn123@gmail.com
License: UNKNOWN
Platform: UNKNOWN
Classifier: Programming Language :: Python :: 3
Classifier: License :: OSI Approved :: MIT License
Classifier: Operating System :: OS Independent
